{"builtWith":"0.15.4","comments":[],"decls":[{"annotation":{"meta":{"metaType":"IsTypeClassConstructor"},"sourceSpan":{"end":[57,84],"start":[56,1]}},"bindType":"NonRec","expression":{"annotation":{"meta":{"metaType":"IsNewtype"},"sourceSpan":{"end":[57,84],"start":[56,1]}},"argument":"x","body":{"annotation":{"meta":null,"sourceSpan":{"end":[57,84],"start":[56,1]}},"type":"Var","value":{"identifier":"x","sourcePos":[0,0]}},"type":"Abs"},"identifier":"ShowRecordFields$Dict"},{"annotation":{"meta":{"metaType":"IsTypeClassConstructor"},"sourceSpan":{"end":[18,22],"start":[17,1]}},"bindType":"NonRec","expression":{"annotation":{"meta":{"metaType":"IsNewtype"},"sourceSpan":{"end":[18,22],"start":[17,1]}},"argument":"x","body":{"annotation":{"meta":null,"sourceSpan":{"end":[18,22],"start":[17,1]}},"type":"Var","value":{"identifier":"x","sourcePos":[0,0]}},"type":"Abs"},"identifier":"Show$Dict"},{"annotation":{"meta":null,"sourceSpan":{"end":[34,24],"start":[33,1]}},"bindType":"NonRec","expression":{"abstraction":{"annotation":{"meta":{"metaType":"IsNewtype"},"sourceSpan":{"end":[34,24],"start":[33,1]}},"type":"Var","value":{"identifier":"Show$Dict","moduleName":["Data","Show"]}},"annotation":{"meta":null,"sourceSpan":{"end":[34,24],"start":[33,1]}},"argument":{"annotation":{"meta":null,"sourceSpan":{"end":[34,24],"start":[33,1]}},"type":"Literal","value":{"literalType":"ObjectLiteral","value":[["show",{"annotation":{"meta":{"metaType":"IsForeign"},"sourceSpan":{"end":[34,24],"start":[34,10]}},"type":"Var","value":{"identifier":"showStringImpl","moduleName":["Data","Show"]}}]]}},"type":"App"},"identifier":"showString"},{"annotation":{"meta":null,"sourceSpan":{"end":[60,28],"start":[59,1]}},"bindType":"NonRec","expression":{"abstraction":{"annotation":{"meta":{"metaType":"IsNewtype"},"sourceSpan":{"end":[60,28],"start":[59,1]}},"type":"Var","value":{"identifier":"ShowRecordFields$Dict","moduleName":["Data","Show"]}},"annotation":{"meta":null,"sourceSpan":{"end":[60,28],"start":[59,1]}},"argument":{"annotation":{"meta":null,"sourceSpan":{"end":[60,28],"start":[59,1]}},"type":"Literal","value":{"literalType":"ObjectLiteral","value":[["showRecordFields",{"annotation":{"meta":null,"sourceSpan":{"end":[60,28],"start":[59,1]}},"argument":"v","body":{"annotation":{"meta":null,"sourceSpan":{"end":[60,28],"start":[59,1]}},"argument":"v1","body":{"annotation":{"meta":null,"sourceSpan":{"end":[60,28],"start":[60,26]}},"type":"Literal","value":{"literalType":"ArrayLiteral","value":[]}},"type":"Abs"},"type":"Abs"}]]}},"type":"App"},"identifier":"showRecordFieldsNil"},{"annotation":{"meta":null,"sourceSpan":{"end":[57,84],"start":[57,3]}},"bindType":"NonRec","expression":{"annotation":{"meta":null,"sourceSpan":{"end":[57,84],"start":[57,3]}},"argument":"dict","body":{"annotation":{"meta":null,"sourceSpan":{"end":[57,84],"start":[57,3]}},"caseAlternatives":[{"binders":[{"annotation":{"meta":{"metaType":"IsNewtype"},"sourceSpan":{"end":[57,84],"start":[57,3]}},"binderType":"ConstructorBinder","binders":[{"annotation":{"meta":null,"sourceSpan":{"end":[57,84],"start":[57,3]}},"binderType":"VarBinder","identifier":"v"}],"constructorName":{"identifier":"ShowRecordFields$Dict","moduleName":["Data","Show"]},"typeName":{"identifier":"ShowRecordFields$Dict","moduleName":["Data","Show"]}}],"expression":{"annotation":{"meta":null,"sourceSpan":{"end":[57,84],"start":[57,3]}},"expression":{"annotation":{"meta":null,"sourceSpan":{"end":[57,84],"start":[57,3]}},"type":"Var","value":{"identifier":"v","sourcePos":[0,0]}},"fieldName":"showRecordFields","type":"Accessor"},"isGuarded":false}],"caseExpressions":[{"annotation":{"meta":null,"sourceSpan":{"end":[57,84],"start":[57,3]}},"type":"Var","value":{"identifier":"dict","sourcePos":[0,0]}}],"type":"Case"},"type":"Abs"},"identifier":"showRecordFields"},{"annotation":{"meta":null,"sourceSpan":{"end":[51,66],"start":[48,1]}},"bindType":"NonRec","expression":{"annotation":{"meta":null,"sourceSpan":{"end":[51,66],"start":[48,1]}},"argument":"$__unused","body":{"annotation":{"meta":null,"sourceSpan":{"end":[51,66],"start":[48,1]}},"argument":"dictShowRecordFields","body":{"annotation":{"meta":null,"sourceSpan":{"end":[0,0],"start":[0,0]}},"binds":[{"annotation":{"meta":null,"sourceSpan":{"end":[0,0],"start":[0,0]}},"bindType":"NonRec","expression":{"abstraction":{"annotation":{"meta":null,"sourceSpan":{"end":[49,38],"start":[49,22]}},"type":"Var","value":{"identifier":"showRecordFields","moduleName":["Data","Show"]}},"annotation":{"meta":{"metaType":"IsSyntheticApp"},"sourceSpan":{"end":[49,58],"start":[49,22]}},"argument":{"annotation":{"meta":null,"sourceSpan":{"end":[0,0],"start":[0,0]}},"type":"Var","value":{"identifier":"dictShowRecordFields","sourcePos":[0,0]}},"type":"App"},"identifier":"showRecordFields1"}],"expression":{"abstraction":{"annotation":{"meta":{"metaType":"IsNewtype"},"sourceSpan":{"end":[51,66],"start":[48,1]}},"type":"Var","value":{"identifier":"Show$Dict","moduleName":["Data","Show"]}},"annotation":{"meta":null,"sourceSpan":{"end":[51,66],"start":[48,1]}},"argument":{"annotation":{"meta":null,"sourceSpan":{"end":[51,66],"start":[48,1]}},"type":"Literal","value":{"literalType":"ObjectLiteral","value":[["show",{"annotation":{"meta":null,"sourceSpan":{"end":[51,66],"start":[48,1]}},"argument":"record","body":{"annotation":{"meta":null,"sourceSpan":{"end":[51,66],"start":[49,17]}},"binds":[{"annotation":{"meta":null,"sourceSpan":{"end":[51,66],"start":[48,1]}},"bindType":"NonRec","expression":{"abstraction":{"abstraction":{"annotation":{"meta":null,"sourceSpan":{"end":[0,0],"start":[0,0]}},"type":"Var","value":{"identifier":"showRecordFields1","sourcePos":[0,0]}},"annotation":{"meta":null,"sourceSpan":{"end":[49,58],"start":[49,22]}},"argument":{"annotation":{"meta":{"constructorType":"ProductType","identifiers":[],"metaType":"IsConstructor"},"sourceSpan":{"end":[49,45],"start":[49,40]}},"type":"Var","value":{"identifier":"Proxy","moduleName":["Type","Proxy"]}},"type":"App"},"annotation":{"meta":null,"sourceSpan":{"end":[49,65],"start":[49,22]}},"argument":{"annotation":{"meta":null,"sourceSpan":{"end":[49,65],"start":[49,59]}},"type":"Var","value":{"identifier":"record","sourcePos":[49,3]}},"type":"App"},"identifier":"v"}],"expression":{"annotation":{"meta":null,"sourceSpan":{"end":[51,66],"start":[49,17]}},"caseAlternatives":[{"binders":[{"annotation":{"meta":null,"sourceSpan":{"end":[50,7],"start":[50,5]}},"binderType":"LiteralBinder","literal":{"literalType":"ArrayLiteral","value":[]}}],"expression":{"annotation":{"meta":null,"sourceSpan":{"end":[50,15],"start":[50,11]}},"type":"Literal","value":{"literalType":"StringLiteral","value":"{}"}},"isGuarded":false},{"binders":[{"annotation":{"meta":null,"sourceSpan":{"end":[51,11],"start":[51,5]}},"binderType":"VarBinder","identifier":"fields"}],"expression":{"abstraction":{"abstraction":{"annotation":{"meta":{"metaType":"IsForeign"},"sourceSpan":{"end":[51,26],"start":[51,15]}},"type":"Var","value":{"identifier":"intercalate","moduleName":["Data","Show"]}},"annotation":{"meta":null,"sourceSpan":{"end":[51,30],"start":[51,15]}},"argument":{"annotation":{"meta":null,"sourceSpan":{"end":[51,30],"start":[51,27]}},"type":"Literal","value":{"literalType":"StringLiteral","value":" "}},"type":"App"},"annotation":{"meta":null,"sourceSpan":{"end":[51,66],"start":[51,15]}},"argument":{"annotation":{"meta":null,"sourceSpan":{"end":[51,66],"start":[51,31]}},"type":"Literal","value":{"literalType":"ArrayLiteral","value":[{"annotation":{"meta":null,"sourceSpan":{"end":[51,35],"start":[51,32]}},"type":"Literal","value":{"literalType":"StringLiteral","value":"{"}},{"abstraction":{"abstraction":{"annotation":{"meta":{"metaType":"IsForeign"},"sourceSpan":{"end":[51,48],"start":[51,37]}},"type":"Var","value":{"identifier":"intercalate","moduleName":["Data","Show"]}},"annotation":{"meta":null,"sourceSpan":{"end":[51,53],"start":[51,37]}},"argument":{"annotation":{"meta":null,"sourceSpan":{"end":[51,53],"start":[51,49]}},"type":"Literal","value":{"literalType":"StringLiteral","value":", "}},"type":"App"},"annotation":{"meta":null,"sourceSpan":{"end":[51,60],"start":[51,37]}},"argument":{"annotation":{"meta":null,"sourceSpan":{"end":[51,60],"start":[51,54]}},"type":"Var","value":{"identifier":"fields","sourcePos":[51,5]}},"type":"App"},{"annotation":{"meta":null,"sourceSpan":{"end":[51,65],"start":[51,62]}},"type":"Literal","value":{"literalType":"StringLiteral","value":"}"}}]}},"type":"App"},"isGuarded":false}],"caseExpressions":[{"annotation":{"meta":null,"sourceSpan":{"end":[51,66],"start":[48,1]}},"type":"Var","value":{"identifier":"v","sourcePos":[0,0]}}],"type":"Case"},"type":"Let"},"type":"Abs"}]]}},"type":"App"},"type":"Let"},"type":"Abs"},"type":"Abs"},"identifier":"showRecord"},{"annotation":{"meta":null,"sourceSpan":{"end":[46,20],"start":[45,1]}},"bindType":"NonRec","expression":{"abstraction":{"annotation":{"meta":{"metaType":"IsNewtype"},"sourceSpan":{"end":[46,20],"start":[45,1]}},"type":"Var","value":{"identifier":"Show$Dict","moduleName":["Data","Show"]}},"annotation":{"meta":null,"sourceSpan":{"end":[46,20],"start":[45,1]}},"argument":{"annotation":{"meta":null,"sourceSpan":{"end":[46,20],"start":[45,1]}},"type":"Literal","value":{"literalType":"ObjectLiteral","value":[["show",{"annotation":{"meta":null,"sourceSpan":{"end":[46,20],"start":[45,1]}},"argument":"v","body":{"annotation":{"meta":null,"sourceSpan":{"end":[46,20],"start":[46,12]}},"type":"Literal","value":{"literalType":"StringLiteral","value":"Proxy3"}},"type":"Abs"}]]}},"type":"App"},"identifier":"showProxy3"},{"annotation":{"meta":null,"sourceSpan":{"end":[43,20],"start":[42,1]}},"bindType":"NonRec","expression":{"abstraction":{"annotation":{"meta":{"metaType":"IsNewtype"},"sourceSpan":{"end":[43,20],"start":[42,1]}},"type":"Var","value":{"identifier":"Show$Dict","moduleName":["Data","Show"]}},"annotation":{"meta":null,"sourceSpan":{"end":[43,20],"start":[42,1]}},"argument":{"annotation":{"meta":null,"sourceSpan":{"end":[43,20],"start":[42,1]}},"type":"Literal","value":{"literalType":"ObjectLiteral","value":[["show",{"annotation":{"meta":null,"sourceSpan":{"end":[43,20],"start":[42,1]}},"argument":"v","body":{"annotation":{"meta":null,"sourceSpan":{"end":[43,20],"start":[43,12]}},"type":"Literal","value":{"literalType":"StringLiteral","value":"Proxy2"}},"type":"Abs"}]]}},"type":"App"},"identifier":"showProxy2"},{"annotation":{"meta":null,"sourceSpan":{"end":[40,19],"start":[39,1]}},"bindType":"NonRec","expression":{"abstraction":{"annotation":{"meta":{"metaType":"IsNewtype"},"sourceSpan":{"end":[40,19],"start":[39,1]}},"type":"Var","value":{"identifier":"Show$Dict","moduleName":["Data","Show"]}},"annotation":{"meta":null,"sourceSpan":{"end":[40,19],"start":[39,1]}},"argument":{"annotation":{"meta":null,"sourceSpan":{"end":[40,19],"start":[39,1]}},"type":"Literal","value":{"literalType":"ObjectLiteral","value":[["show",{"annotation":{"meta":null,"sourceSpan":{"end":[40,19],"start":[39,1]}},"argument":"v","body":{"annotation":{"meta":null,"sourceSpan":{"end":[40,19],"start":[40,12]}},"type":"Literal","value":{"literalType":"StringLiteral","value":"Proxy"}},"type":"Abs"}]]}},"type":"App"},"identifier":"showProxy"},{"annotation":{"meta":null,"sourceSpan":{"end":[28,24],"start":[27,1]}},"bindType":"NonRec","expression":{"abstraction":{"annotation":{"meta":{"metaType":"IsNewtype"},"sourceSpan":{"end":[28,24],"start":[27,1]}},"type":"Var","value":{"identifier":"Show$Dict","moduleName":["Data","Show"]}},"annotation":{"meta":null,"sourceSpan":{"end":[28,24],"start":[27,1]}},"argument":{"annotation":{"meta":null,"sourceSpan":{"end":[28,24],"start":[27,1]}},"type":"Literal","value":{"literalType":"ObjectLiteral","value":[["show",{"annotation":{"meta":{"metaType":"IsForeign"},"sourceSpan":{"end":[28,24],"start":[28,10]}},"type":"Var","value":{"identifier":"showNumberImpl","moduleName":["Data","Show"]}}]]}},"type":"App"},"identifier":"showNumber"},{"annotation":{"meta":null,"sourceSpan":{"end":[25,21],"start":[24,1]}},"bindType":"NonRec","expression":{"abstraction":{"annotation":{"meta":{"metaType":"IsNewtype"},"sourceSpan":{"end":[25,21],"start":[24,1]}},"type":"Var","value":{"identifier":"Show$Dict","moduleName":["Data","Show"]}},"annotation":{"meta":null,"sourceSpan":{"end":[25,21],"start":[24,1]}},"argument":{"annotation":{"meta":null,"sourceSpan":{"end":[25,21],"start":[24,1]}},"type":"Literal","value":{"literalType":"ObjectLiteral","value":[["show",{"annotation":{"meta":{"metaType":"IsForeign"},"sourceSpan":{"end":[25,21],"start":[25,10]}},"type":"Var","value":{"identifier":"showIntImpl","moduleName":["Data","Show"]}}]]}},"type":"App"},"identifier":"showInt"},{"annotation":{"meta":null,"sourceSpan":{"end":[31,22],"start":[30,1]}},"bindType":"NonRec","expression":{"abstraction":{"annotation":{"meta":{"metaType":"IsNewtype"},"sourceSpan":{"end":[31,22],"start":[30,1]}},"type":"Var","value":{"identifier":"Show$Dict","moduleName":["Data","Show"]}},"annotation":{"meta":null,"sourceSpan":{"end":[31,22],"start":[30,1]}},"argument":{"annotation":{"meta":null,"sourceSpan":{"end":[31,22],"start":[30,1]}},"type":"Literal","value":{"literalType":"ObjectLiteral","value":[["show",{"annotation":{"meta":{"metaType":"IsForeign"},"sourceSpan":{"end":[31,22],"start":[31,10]}},"type":"Var","value":{"identifier":"showCharImpl","moduleName":["Data","Show"]}}]]}},"type":"App"},"identifier":"showChar"},{"annotation":{"meta":null,"sourceSpan":{"end":[22,23],"start":[20,1]}},"bindType":"NonRec","expression":{"abstraction":{"annotation":{"meta":{"metaType":"IsNewtype"},"sourceSpan":{"end":[22,23],"start":[20,1]}},"type":"Var","value":{"identifier":"Show$Dict","moduleName":["Data","Show"]}},"annotation":{"meta":null,"sourceSpan":{"end":[22,23],"start":[20,1]}},"argument":{"annotation":{"meta":null,"sourceSpan":{"end":[22,23],"start":[20,1]}},"type":"Literal","value":{"literalType":"ObjectLiteral","value":[["show",{"annotation":{"meta":null,"sourceSpan":{"end":[22,23],"start":[20,1]}},"argument":"v","body":{"annotation":{"meta":null,"sourceSpan":{"end":[22,23],"start":[20,1]}},"caseAlternatives":[{"binders":[{"annotation":{"meta":null,"sourceSpan":{"end":[21,12],"start":[21,8]}},"binderType":"LiteralBinder","literal":{"literalType":"BooleanLiteral","value":true}}],"expression":{"annotation":{"meta":null,"sourceSpan":{"end":[21,21],"start":[21,15]}},"type":"Literal","value":{"literalType":"StringLiteral","value":"true"}},"isGuarded":false},{"binders":[{"annotation":{"meta":null,"sourceSpan":{"end":[22,13],"start":[22,8]}},"binderType":"LiteralBinder","literal":{"literalType":"BooleanLiteral","value":false}}],"expression":{"annotation":{"meta":null,"sourceSpan":{"end":[22,23],"start":[22,16]}},"type":"Literal","value":{"literalType":"StringLiteral","value":"false"}},"isGuarded":false}],"caseExpressions":[{"annotation":{"meta":null,"sourceSpan":{"end":[21,21],"start":[21,3]}},"type":"Var","value":{"identifier":"v","sourcePos":[21,3]}}],"type":"Case"},"type":"Abs"}]]}},"type":"App"},"identifier":"showBoolean"},{"annotation":{"meta":null,"sourceSpan":{"end":[18,22],"start":[18,3]}},"bindType":"NonRec","expression":{"annotation":{"meta":null,"sourceSpan":{"end":[18,22],"start":[18,3]}},"argument":"dict","body":{"annotation":{"meta":null,"sourceSpan":{"end":[18,22],"start":[18,3]}},"caseAlternatives":[{"binders":[{"annotation":{"meta":{"metaType":"IsNewtype"},"sourceSpan":{"end":[18,22],"start":[18,3]}},"binderType":"ConstructorBinder","binders":[{"annotation":{"meta":null,"sourceSpan":{"end":[18,22],"start":[18,3]}},"binderType":"VarBinder","identifier":"v"}],"constructorName":{"identifier":"Show$Dict","moduleName":["Data","Show"]},"typeName":{"identifier":"Show$Dict","moduleName":["Data","Show"]}}],"expression":{"annotation":{"meta":null,"sourceSpan":{"end":[18,22],"start":[18,3]}},"expression":{"annotation":{"meta":null,"sourceSpan":{"end":[18,22],"start":[18,3]}},"type":"Var","value":{"identifier":"v","sourcePos":[0,0]}},"fieldName":"show","type":"Accessor"},"isGuarded":false}],"caseExpressions":[{"annotation":{"meta":null,"sourceSpan":{"end":[18,22],"start":[18,3]}},"type":"Var","value":{"identifier":"dict","sourcePos":[0,0]}}],"type":"Case"},"type":"Abs"},"identifier":"show"},{"annotation":{"meta":null,"sourceSpan":{"end":[37,28],"start":[36,1]}},"bindType":"NonRec","expression":{"annotation":{"meta":null,"sourceSpan":{"end":[37,28],"start":[36,1]}},"argument":"dictShow","body":{"abstraction":{"annotation":{"meta":{"metaType":"IsNewtype"},"sourceSpan":{"end":[37,28],"start":[36,1]}},"type":"Var","value":{"identifier":"Show$Dict","moduleName":["Data","Show"]}},"annotation":{"meta":null,"sourceSpan":{"end":[37,28],"start":[36,1]}},"argument":{"annotation":{"meta":null,"sourceSpan":{"end":[37,28],"start":[36,1]}},"type":"Literal","value":{"literalType":"ObjectLiteral","value":[["show",{"abstraction":{"annotation":{"meta":{"metaType":"IsForeign"},"sourceSpan":{"end":[37,23],"start":[37,10]}},"type":"Var","value":{"identifier":"showArrayImpl","moduleName":["Data","Show"]}},"annotation":{"meta":null,"sourceSpan":{"end":[37,28],"start":[37,10]}},"argument":{"abstraction":{"annotation":{"meta":null,"sourceSpan":{"end":[37,28],"start":[37,24]}},"type":"Var","value":{"identifier":"show","moduleName":["Data","Show"]}},"annotation":{"meta":{"metaType":"IsSyntheticApp"},"sourceSpan":{"end":[37,28],"start":[37,24]}},"argument":{"annotation":{"meta":null,"sourceSpan":{"end":[0,0],"start":[0,0]}},"type":"Var","value":{"identifier":"dictShow","sourcePos":[0,0]}},"type":"App"},"type":"App"}]]}},"type":"App"},"type":"Abs"},"identifier":"showArray"},{"annotation":{"meta":null,"sourceSpan":{"end":[73,66],"start":[62,1]}},"bindType":"NonRec","expression":{"annotation":{"meta":null,"sourceSpan":{"end":[73,66],"start":[62,1]}},"argument":"dictIsSymbol","body":{"annotation":{"meta":null,"sourceSpan":{"end":[0,0],"start":[0,0]}},"binds":[{"annotation":{"meta":null,"sourceSpan":{"end":[0,0],"start":[0,0]}},"bindType":"NonRec","expression":{"abstraction":{"annotation":{"meta":{"metaType":"IsForeign"},"sourceSpan":{"end":[71,26],"start":[71,13]}},"type":"Var","value":{"identifier":"reflectSymbol","moduleName":["Data","Symbol"]}},"annotation":{"meta":{"metaType":"IsSyntheticApp"},"sourceSpan":{"end":[71,47],"start":[71,13]}},"argument":{"annotation":{"meta":null,"sourceSpan":{"end":[0,0],"start":[0,0]}},"type":"Var","value":{"identifier":"dictIsSymbol","sourcePos":[0,0]}},"type":"App"},"identifier":"reflectSymbol"}],"expression":{"annotation":{"meta":null,"sourceSpan":{"end":[73,66],"start":[62,1]}},"argument":"dictShowRecordFields","body":{"annotation":{"meta":null,"sourceSpan":{"end":[0,0],"start":[0,0]}},"binds":[{"annotation":{"meta":null,"sourceSpan":{"end":[0,0],"start":[0,0]}},"bindType":"NonRec","expression":{"abstraction":{"annotation":{"meta":null,"sourceSpan":{"end":[73,30],"start":[73,14]}},"type":"Var","value":{"identifier":"showRecordFields","moduleName":["Data","Show"]}},"annotation":{"meta":{"metaType":"IsSyntheticApp"},"sourceSpan":{"end":[73,59],"start":[73,14]}},"argument":{"annotation":{"meta":null,"sourceSpan":{"end":[0,0],"start":[0,0]}},"type":"Var","value":{"identifier":"dictShowRecordFields","sourcePos":[0,0]}},"type":"App"},"identifier":"showRecordFields1"}],"expression":{"annotation":{"meta":null,"sourceSpan":{"end":[73,66],"start":[62,1]}},"argument":"dictShow","body":{"annotation":{"meta":null,"sourceSpan":{"end":[0,0],"start":[0,0]}},"binds":[{"annotation":{"meta":null,"sourceSpan":{"end":[0,0],"start":[0,0]}},"bindType":"NonRec","expression":{"abstraction":{"annotation":{"meta":null,"sourceSpan":{"end":[69,41],"start":[69,37]}},"type":"Var","value":{"identifier":"show","moduleName":["Data","Show"]}},"annotation":{"meta":{"metaType":"IsSyntheticApp"},"sourceSpan":{"end":[69,47],"start":[69,37]}},"argument":{"annotation":{"meta":null,"sourceSpan":{"end":[0,0],"start":[0,0]}},"type":"Var","value":{"identifier":"dictShow","sourcePos":[0,0]}},"type":"App"},"identifier":"show1"}],"expression":{"abstraction":{"annotation":{"meta":{"metaType":"IsNewtype"},"sourceSpan":{"end":[73,66],"start":[62,1]}},"type":"Var","value":{"identifier":"ShowRecordFields$Dict","moduleName":["Data","Show"]}},"annotation":{"meta":null,"sourceSpan":{"end":[73,66],"start":[62,1]}},"argument":{"annotation":{"meta":null,"sourceSpan":{"end":[73,66],"start":[62,1]}},"type":"Literal","value":{"literalType":"ObjectLiteral","value":[["showRecordFields",{"annotation":{"meta":null,"sourceSpan":{"end":[73,66],"start":[62,1]}},"argument":"v","body":{"annotation":{"meta":null,"sourceSpan":{"end":[73,66],"start":[62,1]}},"argument":"record","body":{"annotation":{"meta":{"metaType":"IsWhere"},"sourceSpan":{"end":[69,55],"start":[69,7]}},"binds":[{"annotation":{"meta":null,"sourceSpan":{"end":[73,66],"start":[73,7]}},"bindType":"NonRec","expression":{"abstraction":{"abstraction":{"annotation":{"meta":null,"sourceSpan":{"end":[0,0],"start":[0,0]}},"type":"Var","value":{"identifier":"showRecordFields1","sourcePos":[0,0]}},"annotation":{"meta":null,"sourceSpan":{"end":[73,59],"start":[73,14]}},"argument":{"annotation":{"meta":{"constructorType":"ProductType","identifiers":[],"metaType":"IsConstructor"},"sourceSpan":{"end":[73,37],"start":[73,32]}},"type":"Var","value":{"identifier":"Proxy","moduleName":["Type","Proxy"]}},"type":"App"},"annotation":{"meta":null,"sourceSpan":{"end":[73,66],"start":[73,14]}},"argument":{"annotation":{"meta":null,"sourceSpan":{"end":[73,66],"start":[73,60]}},"type":"Var","value":{"identifier":"record","sourcePos":[68,3]}},"type":"App"},"identifier":"tail"},{"annotation":{"meta":null,"sourceSpan":{"end":[71,47],"start":[71,7]}},"bindType":"NonRec","expression":{"abstraction":{"annotation":{"meta":null,"sourceSpan":{"end":[0,0],"start":[0,0]}},"type":"Var","value":{"identifier":"reflectSymbol","sourcePos":[0,0]}},"annotation":{"meta":null,"sourceSpan":{"end":[71,47],"start":[71,13]}},"argument":{"annotation":{"meta":{"constructorType":"ProductType","identifiers":[],"metaType":"IsConstructor"},"sourceSpan":{"end":[71,33],"start":[71,28]}},"type":"Var","value":{"identifier":"Proxy","moduleName":["Type","Proxy"]}},"type":"App"},"identifier":"key"},{"annotation":{"meta":null,"sourceSpan":{"end":[72,44],"start":[72,7]}},"bindType":"NonRec","expression":{"abstraction":{"abstraction":{"annotation":{"meta":{"metaType":"IsForeign"},"sourceSpan":{"end":[72,24],"start":[72,15]}},"type":"Var","value":{"identifier":"unsafeGet","moduleName":["Record","Unsafe"]}},"annotation":{"meta":null,"sourceSpan":{"end":[72,28],"start":[72,15]}},"argument":{"annotation":{"meta":null,"sourceSpan":{"end":[72,28],"start":[72,25]}},"type":"Var","value":{"identifier":"key","sourcePos":[71,7]}},"type":"App"},"annotation":{"meta":null,"sourceSpan":{"end":[72,35],"start":[72,15]}},"argument":{"annotation":{"meta":null,"sourceSpan":{"end":[72,35],"start":[72,29]}},"type":"Var","value":{"identifier":"record","sourcePos":[68,3]}},"type":"App"},"identifier":"focus"}],"expression":{"abstraction":{"abstraction":{"annotation":{"meta":{"metaType":"IsForeign"},"sourceSpan":{"end":[69,11],"start":[69,7]}},"type":"Var","value":{"identifier":"cons","moduleName":["Data","Show"]}},"annotation":{"meta":null,"sourceSpan":{"end":[69,50],"start":[69,7]}},"argument":{"abstraction":{"abstraction":{"annotation":{"meta":{"metaType":"IsForeign"},"sourceSpan":{"end":[69,24],"start":[69,13]}},"type":"Var","value":{"identifier":"intercalate","moduleName":["Data","Show"]}},"annotation":{"meta":null,"sourceSpan":{"end":[69,29],"start":[69,13]}},"argument":{"annotation":{"meta":null,"sourceSpan":{"end":[69,29],"start":[69,25]}},"type":"Literal","value":{"literalType":"StringLiteral","value":": "}},"type":"App"},"annotation":{"meta":null,"sourceSpan":{"end":[69,49],"start":[69,13]}},"argument":{"annotation":{"meta":null,"sourceSpan":{"end":[69,49],"start":[69,30]}},"type":"Literal","value":{"literalType":"ArrayLiteral","value":[{"annotation":{"meta":null,"sourceSpan":{"end":[69,35],"start":[69,32]}},"type":"Var","value":{"identifier":"key","sourcePos":[71,7]}},{"abstraction":{"annotation":{"meta":null,"sourceSpan":{"end":[0,0],"start":[0,0]}},"type":"Var","value":{"identifier":"show1","sourcePos":[0,0]}},"annotation":{"meta":null,"sourceSpan":{"end":[69,47],"start":[69,37]}},"argument":{"annotation":{"meta":null,"sourceSpan":{"end":[69,47],"start":[69,42]}},"type":"Var","value":{"identifier":"focus","sourcePos":[72,7]}},"type":"App"}]}},"type":"App"},"type":"App"},"annotation":{"meta":null,"sourceSpan":{"end":[69,55],"start":[69,7]}},"argument":{"annotation":{"meta":null,"sourceSpan":{"end":[69,55],"start":[69,51]}},"type":"Var","value":{"identifier":"tail","sourcePos":[73,7]}},"type":"App"},"type":"Let"},"type":"Abs"},"type":"Abs"}]]}},"type":"App"},"type":"Let"},"type":"Abs"},"type":"Let"},"type":"Abs"},"type":"Let"},"type":"Abs"},"identifier":"showRecordFieldsCons"}],"exports":["show","showRecordFields","showBoolean","showInt","showNumber","showChar","showString","showArray","showProxy","showProxy2","showProxy3","showRecord","showRecordFieldsNil","showRecordFieldsCons"],"foreign":["showIntImpl","showNumberImpl","showCharImpl","showStringImpl","showArrayImpl","cons","intercalate"],"imports":[{"annotation":{"meta":null,"sourceSpan":{"end":[81,63],"start":[1,1]}},"moduleName":["Data","Show"]},{"annotation":{"meta":null,"sourceSpan":{"end":[81,63],"start":[1,1]}},"moduleName":["Data","Symbol"]},{"annotation":{"meta":null,"sourceSpan":{"end":[81,63],"start":[1,1]}},"moduleName":["Prim"]},{"annotation":{"meta":null,"sourceSpan":{"end":[7,26],"start":[7,1]}},"moduleName":["Prim","RowList"]},{"annotation":{"meta":null,"sourceSpan":{"end":[81,63],"start":[1,1]}},"moduleName":["Record","Unsafe"]},{"annotation":{"meta":null,"sourceSpan":{"end":[81,63],"start":[1,1]}},"moduleName":["Type","Proxy"]}],"moduleName":["Data","Show"],"modulePath":".spago/prelude/master/src/Data/Show.purs","reExports":{},"sourceSpan":{"end":[81,63],"start":[1,1]}}